LICENSE.txt
README.md
setup.cfg
setup.py
targa/__init__.py
targa/database.py
targa/keys.py
targa/model.py
targa.egg-info/PKG-INFO
targa.egg-info/SOURCES.txt
targa.egg-info/dependency_links.txt
targa.egg-info/requires.txt
targa.egg-info/top_level.txt
targa/errors/__init__.py
targa/errors/initializationerror.py
targa/errors/mysqlerrors.py
targa/errors/substerror.py