Metadata-Version: 2.1
Name: targa
Version: 1.0.3
Summary: A lightweight async Python library for MySQL queries and modeling.
Home-page: https://github.com/whdev1/targa
Author: whdev1
Author-email: whdev1@protonmail.com
License: MIT
Download-URL: https://github.com/whdev1/targa/archive/refs/tags/v1.0.3.tar.gz
Keywords: Targa,SQL,MySQL,async
Platform: UNKNOWN
Classifier: Development Status :: 3 - Alpha
Classifier: Intended Audience :: Developers
Classifier: Topic :: Software Development :: Build Tools
Classifier: License :: OSI Approved :: MIT License
Classifier: Programming Language :: Python :: 3.9
Classifier: Programming Language :: Python :: 3.10
License-File: LICENSE.txt
